{"cameraMode":{"drawMode":0,"name":"Shaded","section":"Shading Mode"},"sceneLighting":true,"audioPlay":false,"sceneViewState":{"showFog":true,"showMaterialUpdate":false,"showSkybox":true,"showFlares":true,"showImageEffects":true,"showParticleSystems":true},"in2DMode":false,"pivot":{"x":60.30241775512695,"y":-19.678213119506837,"z":126.87104797363281},"rotation":{"x":0.22833476960659028,"y":0.11070755124092102,"z":-0.026143604889512063,"w":0.9669144749641419},"size":99.51847839355469,"orthographic":false}